zubie_api/__init__.py
zubie_api/client.py
zubie_api-0.1.dist-info/LICENSE
zubie_api-0.1.dist-info/METADATA
zubie_api-0.1.dist-info/WHEEL
zubie_api-0.1.dist-info/top_level.txt
zubie_api-0.1.dist-info/RECORD
